another_ping/__init__.py
another_ping/ping.py
another_ping-0.1.dist-info/DESCRIPTION.rst
another_ping-0.1.dist-info/METADATA
another_ping-0.1.dist-info/RECORD
another_ping-0.1.dist-info/WHEEL
another_ping-0.1.dist-info/metadata.json
another_ping-0.1.dist-info/top_level.txt
