Metadata-Version: 1.1
Name: another_ping
Version: 0.1
Summary: Yet another ping module
Home-page: UNKNOWN
Author: SgDylan
Author-email: i@acg.works
License: MIT
Keywords: ping python
Platform: UNKNOWN
Classifier: Development Status :: 4 - Beta
Classifier: Intended Audience :: System Administrators
Classifier: Intended Audience :: Developers
Classifier: Topic :: Internet
Classifier: Topic :: System :: Networking
Classifier: Topic :: System :: Networking :: Monitoring
Classifier: Operating System :: POSIX
Classifier: License :: OSI Approved :: MIT License
Classifier: Programming Language :: Python :: 2
Classifier: Programming Language :: Python :: 3
